mailscout/__init__.py
mailscout/scout.py
mailscout-0.1.1.dist-info/METADATA
mailscout-0.1.1.dist-info/WHEEL
mailscout-0.1.1.dist-info/top_level.txt
mailscout-0.1.1.dist-info/RECORD
