Metadata-Version: 2.1
Name: mailscout
Version: 0.1.1
Summary: MailScout is a Python library designed for finding business email addresses and simple email validation. It offers a range of tools for email validation, SMTP checks, email normalization, and generating potential business email addresses based on common naming conventions/employee name combinations.
Author: Batuhan Akyazı
Author-email: Batuhan Akyazı <batuhanakydev@gmail.com>
Project-URL: Homepage, https://github.com/batuhanaky/mailscout
Keywords: email,marketing,email-finder,email-validation
Classifier: License :: OSI Approved :: MIT License
Classifier: Programming Language :: Python
Classifier: Programming Language :: Python :: 3
Requires-Python: >=3.7
Requires-Dist: dnspython
Requires-Dist: unidecode
Provides-Extra: dev
Requires-Dist: pytest; extra == "dev"
